{
  "id": "898abcb6-ed94-41ee-8f0e-eda46878476c",
  "title": "Product Updates: Updates to Volumes, JS and Go SDKs, and more",
  "source_url": "https://modal.com/blog/modal-product-updates-oct-2025",
  "source_name": "Modal Blog",
  "published_at": "2026-03-19 22:43:56",
  "scraped_at": "2026-03-19 22:43:56",
  "bs_score": 4.5,
  "bs_rating": "mixed",
  "human_bs_score": null,
  "human_bs_rating": null,
  "editorial_comment": null,
  "category": "engineering",
  "ai_summary": null,
  "approved": false,
  "author_name": null
}